dj_push/__init__.py
dj_push/admin.py
dj_push/apps.py
dj_push/models.py
dj_push/serializers.py
dj_push/tests.py
dj_push/urls.py
dj_push/views.py
dj_push/migrations/0001_initial.py
dj_push/migrations/0002_alter_devicetoken_created_date.py
dj_push/migrations/__init__.py
django_push_notification_service_firebash-0.0.1.dist-info/LICENSE
django_push_notification_service_firebash-0.0.1.dist-info/METADATA
django_push_notification_service_firebash-0.0.1.dist-info/WHEEL
django_push_notification_service_firebash-0.0.1.dist-info/top_level.txt
django_push_notification_service_firebash-0.0.1.dist-info/RECORD
