Metadata-Version: 2.1
Name: django-push-notification-service-firebash
Version: 0.0.1
Summary: Use for Firebash Phone Push Notification
Home-page: https://gitlab.com/bajpairitesh878/django_firebash_push_service
Author: Ritesh Bajpai
Author-email: bajpairitesh878@gmail.com
License: MIT
Project-URL: Bug Tracker, https://gitlab.com/bajpairitesh878/django_firebash_push_service/issues
Platform: UNKNOWN
Classifier: Programming Language :: Python :: 3
Classifier: License :: OSI Approved :: MIT License
Classifier: Operating System :: OS Independent
Requires-Python: >=3.6
License-File: LICENSE
Requires-Dist: Django (>=2.2)
